setup.py
migrations/__init__.py
nirvana_ui.egg-info/PKG-INFO
nirvana_ui.egg-info/SOURCES.txt
nirvana_ui.egg-info/dependency_links.txt
nirvana_ui.egg-info/requires.txt
nirvana_ui.egg-info/top_level.txt
templatetags/__init__.py
templatetags/nirvana_tags.py